custom_components/__init__.py
custom_components/constants.py
custom_components/custom_events.py
custom_components/gun.py
custom_components/gyroscope.py
custom_components/health.py
custom_components/npc_behavior.py
custom_components/thruster.py
custom_gos/__init__.py
custom_gos/armed_ship.py
custom_gos/bullet.py
custom_gos/enemy.py
custom_gos/player.py
custom_gos/scene_manager.py
custom_scenes/__init__.py
custom_scenes/ai_test.py
custom_scenes/main_game.py
custom_scenes/terrain_test.py
invasionEngine/__init__.py
invasionEngine/components.py
invasionEngine/constants.py
invasionEngine/events.py
invasionEngine/game_objects.py
invasionEngine/scenes.py
invasionEngine/utils.py
resources/__init__.py
start_menu/Button.py
start_menu/__init__.py
start_menu/game_start_screen.py
start_menu/story_teller.py
unit_test/__init__.py
unit_test/test_rm.py
unit_test/test_utils.py
gameInvasion-3.0.2.dist-info/METADATA
gameInvasion-3.0.2.dist-info/WHEEL
gameInvasion-3.0.2.dist-info/top_level.txt
gameInvasion-3.0.2.dist-info/RECORD
